mcp_server_tos/__init__.py
mcp_server_tos/config.py
mcp_server_tos/main.py
mcp_server_tos/server.py
mcp_server_tos/resources/__init__.py
mcp_server_tos/resources/bucket.py
mcp_server_tos/resources/object.py
mcp_server_tos/resources/service.py
tos_mcp_server-0.1.0.dist-info/METADATA
tos_mcp_server-0.1.0.dist-info/WHEEL
tos_mcp_server-0.1.0.dist-info/entry_points.txt
tos_mcp_server-0.1.0.dist-info/top_level.txt
tos_mcp_server-0.1.0.dist-info/RECORD
