Metadata-Version: 2.4
Name: tos-mcp-server
Version: 0.1.0
Summary: Add your description here
Requires-Python: >=3.13
Requires-Dist: httpx>=0.28.1
Requires-Dist: mcp[cli]>=1.4.1
Requires-Dist: tos>=2.8.1
Requires-Dist: python-dotenv>=1.0.1
Requires-Dist: uvicorn>=0.34.0
